mlfab/__init__.py
mlfab/py.typed
mlfab/requirements.txt
mlfab/core/__init__.py
mlfab/core/conf.py
mlfab/core/state.py
mlfab/nn/__init__.py
mlfab/nn/activations.py
mlfab/nn/embeddings.py
mlfab/nn/functions.py
mlfab/nn/init.py
mlfab/nn/kmeans.py
mlfab/nn/lora.py
mlfab/nn/losses.py
mlfab/nn/lr_schedulers.py
mlfab/nn/norms.py
mlfab/nn/optimizers.py
mlfab/nn/parallel.py
mlfab/nn/architectures/__init__.py
mlfab/nn/architectures/attention.py
mlfab/nn/architectures/bifpn.py
mlfab/nn/architectures/monotonic_attention.py
mlfab/nn/architectures/next_token.py
mlfab/nn/architectures/rnn.py
mlfab/nn/architectures/rwkv.py
mlfab/nn/architectures/unet.py
mlfab/nn/device/__init__.py
mlfab/nn/device/auto.py
mlfab/nn/device/base.py
mlfab/nn/device/cpu.py
mlfab/nn/device/gpu.py
mlfab/nn/device/metal.py
mlfab/nn/diffusion/__init__.py
mlfab/nn/diffusion/consistency.py
mlfab/nn/diffusion/gaussian.py
mlfab/nn/diffusion/ode.py
mlfab/nn/quantization/__init__.py
mlfab/nn/quantization/fsq.py
mlfab/nn/quantization/lfq.py
mlfab/nn/quantization/vq.py
mlfab/nn/triton/__init__.py
mlfab/nn/triton/kmeans.py
mlfab/nn/triton/lion.py
mlfab/nn/triton/monotonic_attention.py
mlfab/nn/triton/rwkv.py
mlfab/task/__init__.py
mlfab/task/base.py
mlfab/task/logger.py
mlfab/task/task.py
mlfab/task/launchers/__init__.py
mlfab/task/launchers/base.py
mlfab/task/launchers/cli.py
mlfab/task/launchers/process.py
mlfab/task/launchers/slurm.py
mlfab/task/launchers/staged.py
mlfab/task/loggers/__init__.py
mlfab/task/loggers/json.py
mlfab/task/loggers/state.py
mlfab/task/loggers/stdout.py
mlfab/task/loggers/tensorboard.py
mlfab/task/mixins/__init__.py
mlfab/task/mixins/artifacts.py
mlfab/task/mixins/checkpointing.py
mlfab/task/mixins/compile.py
mlfab/task/mixins/cpu_stats.py
mlfab/task/mixins/data_loader.py
mlfab/task/mixins/device.py
mlfab/task/mixins/gpu_stats.py
mlfab/task/mixins/logger.py
mlfab/task/mixins/meta.py
mlfab/task/mixins/optimizer.py
mlfab/task/mixins/parallel.py
mlfab/task/mixins/pretrained.py
mlfab-0.2.10.dist-info/LICENSE
mlfab-0.2.10.dist-info/METADATA
mlfab-0.2.10.dist-info/WHEEL
mlfab-0.2.10.dist-info/top_level.txt
mlfab-0.2.10.dist-info/RECORD
