Metadata-Version: 2.2
Name: mlfab
Version: 0.2.10
Summary: A collection of core machine learning tools
Home-page: https://github.com/dpshai/mlfab
Author: Benjamin Bolte
Classifier: Development Status :: 4 - Beta
Classifier: Intended Audience :: Developers
Classifier: Topic :: Scientific/Engineering :: Artificial Intelligence
Classifier: License :: OSI Approved :: MIT License
Classifier: Programming Language :: Python :: 3
Requires-Python: >=3.11
License-File: LICENSE
Requires-Dist: dpshdl
Requires-Dist: GitPython
Requires-Dist: numpy<2.0
Requires-Dist: omegaconf
Requires-Dist: psutil
Requires-Dist: sarfile
Requires-Dist: six
Requires-Dist: smart_open
Requires-Dist: tensorboard
Requires-Dist: torch
Requires-Dist: torchaudio
Requires-Dist: torchvision
Requires-Dist: wcwidth
Provides-Extra: dev
Requires-Dist: black; extra == "dev"
Requires-Dist: darglint; extra == "dev"
Requires-Dist: mypy; extra == "dev"
Requires-Dist: pytest; extra == "dev"
Requires-Dist: pytest-timeout; extra == "dev"
Requires-Dist: ruff; extra == "dev"
Dynamic: author
Dynamic: classifier
Dynamic: description
Dynamic: description-content-type
Dynamic: home-page
Dynamic: provides-extra
Dynamic: requires-dist
Dynamic: requires-python
Dynamic: summary
